streamlit-query-builder/__init__.py
streamlit-query-builder/frontend/build/asset-manifest.json
streamlit-query-builder/frontend/build/bootstrap.min.css
streamlit-query-builder/frontend/build/index.html
streamlit-query-builder/frontend/build/static/css/main.7c3e989d.chunk.css
streamlit-query-builder/frontend/build/static/css/main.7c3e989d.chunk.css.map
streamlit-query-builder/frontend/build/static/js/2.5b46a033.chunk.js
streamlit-query-builder/frontend/build/static/js/2.5b46a033.chunk.js.LICENSE.txt
streamlit-query-builder/frontend/build/static/js/2.5b46a033.chunk.js.map
streamlit-query-builder/frontend/build/static/js/main.12ddfc6e.chunk.js
streamlit-query-builder/frontend/build/static/js/main.12ddfc6e.chunk.js.map
streamlit-query-builder/frontend/build/static/js/runtime-main.d0f35e2d.js
streamlit-query-builder/frontend/build/static/js/runtime-main.d0f35e2d.js.map
streamlit_query_builder/__init__.py
streamlit_query_builder/frontend/build/asset-manifest.json
streamlit_query_builder/frontend/build/bootstrap.min.css
streamlit_query_builder/frontend/build/index.html
streamlit_query_builder/frontend/build/static/css/main.19a0a054.chunk.css
streamlit_query_builder/frontend/build/static/css/main.19a0a054.chunk.css.map
streamlit_query_builder/frontend/build/static/css/main.7c3e989d.chunk.css
streamlit_query_builder/frontend/build/static/css/main.7c3e989d.chunk.css.map
streamlit_query_builder/frontend/build/static/js/2.255db975.chunk.js
streamlit_query_builder/frontend/build/static/js/2.255db975.chunk.js.LICENSE.txt
streamlit_query_builder/frontend/build/static/js/2.255db975.chunk.js.map
streamlit_query_builder/frontend/build/static/js/main.5bd52841.chunk.js
streamlit_query_builder/frontend/build/static/js/main.5bd52841.chunk.js.map
streamlit_query_builder/frontend/build/static/js/main.5e6cc0f5.chunk.js
streamlit_query_builder/frontend/build/static/js/main.5e6cc0f5.chunk.js.map
streamlit_query_builder/frontend/build/static/js/runtime-main.d0f35e2d.js
streamlit_query_builder-0.0.6.dist-info/LICENSE
streamlit_query_builder-0.0.6.dist-info/METADATA
streamlit_query_builder-0.0.6.dist-info/WHEEL
streamlit_query_builder-0.0.6.dist-info/top_level.txt
streamlit_query_builder-0.0.6.dist-info/RECORD
