Metadata-Version: 2.1
Name: streamlit-query-builder
Version: 0.0.6
Summary: react-query-builder interface for streamlit
Home-page: UNKNOWN
Author: Mohammad Falakmasir
Author-email: falakmasir@gmail.com
License: UNKNOWN
Platform: UNKNOWN
Requires-Python: >=3.6
Requires-Dist: streamlit (>=0.63)
